pypi_query_mcp/__init__.py
pypi_query_mcp/config/__init__.py
pypi_query_mcp/config/repository.py
pypi_query_mcp/config/settings.py
pypi_query_mcp/core/__init__.py
pypi_query_mcp/core/dependency_parser.py
pypi_query_mcp/core/exceptions.py
pypi_query_mcp/core/pypi_client.py
pypi_query_mcp/core/stats_client.py
pypi_query_mcp/core/version_utils.py
pypi_query_mcp/prompts/__init__.py
pypi_query_mcp/prompts/dependency_management.py
pypi_query_mcp/prompts/environment_analysis.py
pypi_query_mcp/prompts/migration_guidance.py
pypi_query_mcp/prompts/package_analysis.py
pypi_query_mcp/prompts/trending_analysis.py
pypi_query_mcp/server.py
pypi_query_mcp/tools/__init__.py
pypi_query_mcp/tools/compatibility_check.py
pypi_query_mcp/tools/dependency_resolver.py
pypi_query_mcp/tools/download_stats.py
pypi_query_mcp/tools/package_downloader.py
pypi_query_mcp/tools/package_query.py
pypi_query_mcp_server-0.6.5.dist-info/LICENSE
pypi_query_mcp_server-0.6.5.dist-info/METADATA
pypi_query_mcp_server-0.6.5.dist-info/WHEEL
pypi_query_mcp_server-0.6.5.dist-info/entry_points.txt
pypi_query_mcp_server-0.6.5.dist-info/RECORD
