Metadata-Version: 2.3
Name: pypi-query-mcp-server
Version: 0.6.5
Summary: A Model Context Protocol (MCP) server for querying PyPI package information, dependencies, and compatibility
License: MIT
Keywords: mcp,pypi,package,dependency,python
Author: Hal
Author-email: hal.long@outlook.com
Requires-Python: >=3.10,<4.0
Classifier: Development Status :: 3 - Alpha
Classifier: Intended Audience :: Developers
Classifier: License :: OSI Approved :: MIT License
Classifier: Operating System :: OS Independent
Classifier: Programming Language :: Python :: 3
Classifier: Programming Language :: Python :: 3.10
Classifier: Programming Language :: Python :: 3.11
Classifier: Programming Language :: Python :: 3.12
Classifier: Programming Language :: Python :: 3.13
Classifier: Topic :: Software Development :: Libraries :: Python Modules
Classifier: Topic :: System :: Software Distribution
Requires-Dist: click (>=8.1.0,<9.0.0)
Requires-Dist: fastmcp (>=2.0.0,<3.0.0)
Requires-Dist: httpx (>=0.28.0,<0.29.0)
Requires-Dist: packaging (>=24.0,<25.0)
Requires-Dist: pydantic (>=2.0.0,<3.0.0)
Requires-Dist: pydantic-settings (>=2.0.0,<3.0.0)
Project-URL: Documentation, https://github.com/loonghao/pypi-query-mcp-server
Project-URL: Homepage, https://github.com/loonghao/pypi-query-mcp-server
Project-URL: Repository, https://github.com/loonghao/pypi-query-mcp-server
